{
  "users": [
    {
      "username": "jav",
      "email": "jvk",
      "password": "$2a$10$HVU7gyzR8tzl2HhkWrSLEuuuAh7bOcJe/L9WdY816rjjAg1MfgbTS"
    },
    {
      "username": "uzkhu",
      "email": "usuhu11@gmail.com",
      "password": "$2a$10$Fp16dpqAeapTPEGtwQVJu.VNRpnINvARfPwR82/LgXM6nL8savYsu"
    },
    {
      "username": "gegeenee",
      "email": "gegee.b@gmail.com",
      "password": "$2a$10$IgXfmsMcu73ZlV45JPSyQOIEjPV84Th2EKCPmT5o4OWYYEz8B/ps."
    },
    {
      "username": "amgaa",
      "email": "amgaa1@gmail.com",
      "password": "$2a$10$V00y43IK7JDlhmaxW0XaFeMcBo.gHkw1qN98hBcSxRAeSKEY6XJqW"
    },
    {
      "username": "adsas",
      "email": "qweqw",
      "password": "$2a$10$fKPNHbFj8YxGNvB2B.RkMOXJ7hjSpGbO2ZL4lDGotxp/GB5vkHkXm"
    }
  ]
}
